stc2gii_hack/__init__.py
stc2gii_hack/hack.py
stc2gii_hack/run_hack.py
stc2gii_hack-0.3.5.dist-info/entry_points.txt
stc2gii_hack-0.3.5.dist-info/WHEEL
stc2gii_hack-0.3.5.dist-info/METADATA
stc2gii_hack-0.3.5.dist-info/RECORD
