Metadata-Version: 2.1
Name: stc2gii-hack
Version: 0.3.5
Summary: 
Author: Joshua Teves
Author-email: joshua.teves@nih.gov
Requires-Python: >=3.8,<4.0
Classifier: Programming Language :: Python :: 3
Classifier: Programming Language :: Python :: 3.10
Classifier: Programming Language :: Python :: 3.8
Classifier: Programming Language :: Python :: 3.9
Requires-Dist: mne (>=1.2.1,<2.0.0)
Requires-Dist: nibabel (>=3.2.2,<4.0.0)
Requires-Dist: numpy (>=1.22.3,<2.0.0)
